
{
  "public_root": "./www",
  "resource_path": "./www",
  "specs": [
    {
      "title": "DIF Sidetree Protocol",
      "logo": "https://rawcdn.githack.com/decentralized-identity/decentralized-identity.github.io/a3ca39717e440302d1fd99a796e7f00e1c42eb2d/images/logo-flat.svg",
      "logo_link": "https://identity.foundation",
      "source": {
        "host": "github",
        "account": "decentralized-identity",
        "repo": "sidetree"
      },
      "output_path": "./www/spec",
      "spec_directory": "./docs/spec",
      "markdown_paths": [
        "title.md",
        "abstract.md",
        "intro.md",
        "terminology.md",
        "versioning.md",
        "parameters.md",
        "common-functions.md",
        "topology.md",
        "file-structures.md",
        "did-uri.md",
        "json-web-signatures.md",
        "operations.md",
        "patches.md",
        "processing.md",
        "pof.md",
        "resolution.md",
        "method-versioning.md",
        "context.md",
        "guidelines.md",
        "appendix.md"
      ]
    },
    {
      "title": "DIF Sidetree REST API",
      "logo": "https://rawcdn.githack.com/decentralized-identity/decentralized-identity.github.io/a3ca39717e440302d1fd99a796e7f00e1c42eb2d/images/logo-flat.svg",
      "logo_link": "https://identity.foundation",
      "source": {
        "host": "github",
        "account": "decentralized-identity",
        "repo": "sidetree"
      },
      "output_path": "./www/api",
      "spec_directory": "./docs/api",
      "markdown_paths": [
        "title.md",
        "content.md"
      ]
    }
  ]
}
